LICENSE
MANIFEST.in
README.md
pyproject.toml
mmengine/__init__.py
mmengine/version.py
mmengine/_strategy/__init__.py
mmengine/_strategy/base.py
mmengine/_strategy/colossalai.py
mmengine/_strategy/deepspeed.py
mmengine/_strategy/distributed.py
mmengine/_strategy/fsdp.py
mmengine/_strategy/single_device.py
mmengine/_strategy/utils.py
mmengine/analysis/__init__.py
mmengine/analysis/complexity_analysis.py
mmengine/analysis/jit_analysis.py
mmengine/analysis/jit_handles.py
mmengine/analysis/print_helper.py
mmengine/config/__init__.py
mmengine/config/config.py
mmengine/config/lazy.py
mmengine/config/utils.py
mmengine/dataset/__init__.py
mmengine/dataset/base_dataset.py
mmengine/dataset/dataset_wrapper.py
mmengine/dataset/sampler.py
mmengine/dataset/utils.py
mmengine/device/__init__.py
mmengine/device/utils.py
mmengine/dist/__init__.py
mmengine/dist/dist.py
mmengine/dist/utils.py
mmengine/evaluator/__init__.py
mmengine/evaluator/evaluator.py
mmengine/evaluator/metric.py
mmengine/evaluator/utils.py
mmengine/fileio/__init__.py
mmengine/fileio/file_client.py
mmengine/fileio/io.py
mmengine/fileio/parse.py
mmengine/fileio/backends/__init__.py
mmengine/fileio/backends/base.py
mmengine/fileio/backends/http_backend.py
mmengine/fileio/backends/lmdb_backend.py
mmengine/fileio/backends/local_backend.py
mmengine/fileio/backends/memcached_backend.py
mmengine/fileio/backends/petrel_backend.py
mmengine/fileio/backends/registry_utils.py
mmengine/fileio/handlers/__init__.py
mmengine/fileio/handlers/base.py
mmengine/fileio/handlers/json_handler.py
mmengine/fileio/handlers/pickle_handler.py
mmengine/fileio/handlers/registry_utils.py
mmengine/fileio/handlers/yaml_handler.py
mmengine/hooks/__init__.py
mmengine/hooks/checkpoint_hook.py
mmengine/hooks/early_stopping_hook.py
mmengine/hooks/ema_hook.py
mmengine/hooks/empty_cache_hook.py
mmengine/hooks/hook.py
mmengine/hooks/iter_timer_hook.py
mmengine/hooks/logger_hook.py
mmengine/hooks/naive_visualization_hook.py
onedl_mmengine.egg-info/PKG-INFO
onedl_mmengine.egg-info/SOURCES.txt
onedl_mmengine.egg-info/dependency_links.txt
onedl_mmengine.egg-info/requires.txt
onedl_mmengine.egg-info/top_level.txt