Metadata-Version: 2.4
Name: onedl-mmengine
Version: 0.10.8
Summary: Engine of VBTI projects
Author: OneDL MMEngine Contributors
Author-email: VBTI Contributors <oss-team@vbti.nl>
License: Apache-2.0
Project-URL: Homepage, https://onedl.ai
Project-URL: Repository, https://github.com/VBTI-development/onedl-mmengine
Project-URL: Documentation, https://onedl-mmengine.readthedocs.io/en/latest/
Classifier: Development Status :: 4 - Beta
Classifier: Operating System :: OS Independent
Classifier: Programming Language :: Python :: 3
Classifier: Programming Language :: Python :: 3.10
Classifier: Topic :: Utilities
Requires-Python: >=3.10
License-File: LICENSE
Requires-Dist: addict
Requires-Dist: matplotlib
Requires-Dist: numpy
Requires-Dist: pyyaml
Requires-Dist: rich
Requires-Dist: termcolor
Requires-Dist: yapf
Requires-Dist: regex; sys_platform == "win32"
Provides-Extra: all
Requires-Dist: addict; extra == "all"
Requires-Dist: matplotlib; extra == "all"
Requires-Dist: numpy; extra == "all"
Requires-Dist: pyyaml; extra == "all"
Requires-Dist: rich; extra == "all"
Requires-Dist: termcolor; extra == "all"
Requires-Dist: yapf; extra == "all"
Requires-Dist: regex; sys_platform == "win32" and extra == "all"
Requires-Dist: aim<=3.17.5; sys_platform != "win32" and extra == "all"
Requires-Dist: bitsandbytes; extra == "all"
Requires-Dist: clearml; extra == "all"
Requires-Dist: coverage; extra == "all"
Requires-Dist: dadaptation; extra == "all"
Requires-Dist: dvclive; extra == "all"
Requires-Dist: lion-pytorch; extra == "all"
Requires-Dist: lmdb; extra == "all"
Requires-Dist: mlflow; extra == "all"
Requires-Dist: parameterized; extra == "all"
Requires-Dist: pydantic==1.10.9; extra == "all"
Requires-Dist: pytest; extra == "all"
Requires-Dist: transformers; extra == "all"
Dynamic: license-file
